eqt/__init__.py
eqt/_dist_ver.py
eqt/io.py
eqt/threading/QtThreading.py
eqt/threading/__init__.py
eqt/ui/FormDialog.py
eqt/ui/MainWindowWithProgressDialogs.py
eqt/ui/MainWindowWithSessionManagement.py
eqt/ui/NoBorderScrollArea.py
eqt/ui/ProgressTimerDialog.py
eqt/ui/ReOrderableListWidget.py
eqt/ui/SessionDialogs.py
eqt/ui/UIFormWidget.py
eqt/ui/UIMultiStepWidget.py
eqt/ui/UISliderWidget.py
eqt/ui/UIStackedWidget.py
eqt/ui/__init__.py
eqt-2.0.0.dist-info/LICENSE
eqt-2.0.0.dist-info/METADATA
eqt-2.0.0.dist-info/WHEEL
eqt-2.0.0.dist-info/top_level.txt
eqt-2.0.0.dist-info/RECORD
