Metadata-Version: 2.2
Name: eqt
Version: 2.0.0
Summary: A number of templates and tools to develop Qt GUIs with Python effectively
Author-email: Edoardo Pasca <edoardo.pasca@stfc.ac.uk>, Laura Murgatroyd <laura.murgatroyd@stfc.ac.uk>
Maintainer-email: Casper da Costa-Luis <casper.dcl@physics.org>
License: Apache-2.0
Project-URL: documentation, https://github.com/TomographicImaging/eqt#readme
Project-URL: repository, https://github.com/TomographicImaging/eqt
Project-URL: changelog, https://github.com/TomographicImaging/eqt/releases
Keywords: Qt
Classifier: Development Status :: 4 - Beta
Classifier: License :: OSI Approved :: Apache Software License
Classifier: Operating System :: OS Independent
Classifier: Programming Language :: Python :: 3
Classifier: Programming Language :: Python :: 3.7
Classifier: Programming Language :: Python :: 3.8
Classifier: Programming Language :: Python :: 3.9
Classifier: Programming Language :: Python :: 3.10
Classifier: Programming Language :: Python :: 3.11
Classifier: Programming Language :: Python :: 3 :: Only
Requires-Python: >=3.7
License-File: LICENSE
Requires-Dist: qtpy
Requires-Dist: qdarkstyle
Provides-Extra: dev
Requires-Dist: pytest>=6; extra == "dev"
Requires-Dist: pytest-cov; extra == "dev"
Requires-Dist: pytest-timeout; extra == "dev"
Requires-Dist: unittest_parametrize; extra == "dev"
